vericoin
