Metadata-Version: 1.0
Name: vericoin
Version: 0.1.24
Summary: 암호화폐 Daily 가격 조회
Home-page: https://github.com/sharebook-kr/vericoin
Author: jonghun.yoo
Author-email: jonghun.yoo@outlook.com
License: UNKNOWN
Platform: UNKNOWN
